tinyobjloader.cpython-36m-x86_64-linux-gnu.so
tinyobjloader-0.1.dist-info/METADATA
tinyobjloader-0.1.dist-info/RECORD
tinyobjloader-0.1.dist-info/WHEEL
tinyobjloader-0.1.dist-info/top_level.txt
