Metadata-Version: 2.1
Name: tinyobjloader
Version: 0.1
Summary: Python module for tinyobjloader
Home-page: https://github.com/syoyo/tinyobjloader
Author: Syoyo Fujita
Author-email: syoyo@lighttransport.com
License: UNKNOWN
Platform: UNKNOWN
Classifier: License :: OSI Approved :: MIT License
